tvc/__init__.py
tvc/ammunition.py
tvc/armor.py
tvc/backpack.py
tvc/barter.py
tvc/client.py
tvc/enums.py
tvc/exceptions.py
tvc/food.py
tvc/grenade.py
tvc/headphone.py
tvc/item.py
tvc/key.py
tvc/maps.py
tvc/mixins.py
tvc/requester.py
tvc/utils.py
tvc/types/__init__.py
tvc/types/ammunition.py
tvc/types/armor.py
tvc/types/backpack.py
tvc/types/banned.py
tvc/types/barter.py
tvc/types/cell.py
tvc/types/food.py
tvc/types/grenade.py
tvc/types/headphone.py
tvc/types/item.py
tvc/types/key.py
tvc/types/maps.py
tarkov_changes.py-0.3.0.dist-info/LICENSE
tarkov_changes.py-0.3.0.dist-info/METADATA
tarkov_changes.py-0.3.0.dist-info/WHEEL
tarkov_changes.py-0.3.0.dist-info/top_level.txt
tarkov_changes.py-0.3.0.dist-info/RECORD
