Metadata-Version: 2.1
Name: tarkov-changes.py
Version: 0.3.0
Summary: async API wrapper for Tarkov Changes written in Python.
Home-page: https://github.com/Hostagen/tarkov-changes.py
Author: Hostagen
License: MIT
Requires-Python: >=3.8.0
License-File: LICENSE
